{
  "init": "2026061700",
  "city": {
    "id": "miami_gardens",
    "market": "Miami / Miami Gardens",
    "display_name": "Miami / Miami Gardens",
    "stadium_area": "Hard Rock Stadium area",
    "state": "FL",
    "lat": 25.958,
    "lon": -80.2389,
    "state_view": {
      "label": "Florida",
      "bounds": [
        [
          24.4,
          -87.8
        ],
        [
          31.1,
          -79.8
        ]
      ]
    }
  },
  "nearest_grid": {
    "grid_i": 104,
    "grid_j": 187,
    "grid_lat": 26.0,
    "grid_lon": -80.25
  },
  "box_indices": {
    "i0": 102,
    "i1_exclusive": 107,
    "j0": 185,
    "j1_exclusive": 190
  },
  "n_records": 186,
  "n_lead_records": 31,
  "products": [
    {
      "product_id": "expected_precip",
      "product_label": "Expected precipitation",
      "units": "mm per 12h",
      "nearest_peak": {
        "value": 7.818446159362793,
        "lead_hour": 78,
        "valid_time": "2026-06-20 06:00 UTC"
      },
      "box_max_peak": {
        "value": 11.89698600769043,
        "lead_hour": 78,
        "valid_time": "2026-06-20 06:00 UTC"
      }
    },
    {
      "product_id": "prob_gt_0p5inch_percent",
      "product_label": "Probability > 0.5 inch",
      "units": "%",
      "nearest_peak": {
        "value": 17.16623306274414,
        "lead_hour": 78,
        "valid_time": "2026-06-20 06:00 UTC"
      },
      "box_max_peak": {
        "value": 25.459081649780273,
        "lead_hour": 78,
        "valid_time": "2026-06-20 06:00 UTC"
      }
    },
    {
      "product_id": "prob_gt_1inch_percent",
      "product_label": "Probability > 1 inch",
      "units": "%",
      "nearest_peak": {
        "value": 9.262126922607422,
        "lead_hour": 78,
        "valid_time": "2026-06-20 06:00 UTC"
      },
      "box_max_peak": {
        "value": 14.657073974609375,
        "lead_hour": 78,
        "valid_time": "2026-06-20 06:00 UTC"
      }
    },
    {
      "product_id": "prob_gt_2inch_percent",
      "product_label": "Probability > 2 inch",
      "units": "%",
      "nearest_peak": {
        "value": 3.4560441970825195,
        "lead_hour": 78,
        "valid_time": "2026-06-20 06:00 UTC"
      },
      "box_max_peak": {
        "value": 5.981957912445068,
        "lead_hour": 78,
        "valid_time": "2026-06-20 06:00 UTC"
      }
    },
    {
      "product_id": "prob_gt_2yr12h_ari_percent",
      "product_label": "Probability > 2-year 12-h ARI",
      "units": "%",
      "nearest_peak": {
        "value": 0.3843069076538086,
        "lead_hour": 78,
        "valid_time": "2026-06-20 06:00 UTC"
      },
      "box_max_peak": {
        "value": 1.4638185501098633,
        "lead_hour": 78,
        "valid_time": "2026-06-20 06:00 UTC"
      }
    },
    {
      "product_id": "prob_gt_5yr12h_ari_percent",
      "product_label": "Probability > 5-year 12-h ARI",
      "units": "%",
      "nearest_peak": {
        "value": 0.14240741729736328,
        "lead_hour": 78,
        "valid_time": "2026-06-20 06:00 UTC"
      },
      "box_max_peak": {
        "value": 0.7165789604187012,
        "lead_hour": 78,
        "valid_time": "2026-06-20 06:00 UTC"
      }
    }
  ],
  "files": {
    "timeseries_json": "data/cities/miami_gardens/timeseries_12h.json",
    "timeseries_csv": "data/cities/miami_gardens/timeseries_12h.csv",
    "summary_json": "data/cities/miami_gardens/summary.json"
  },
  "is_sample_data": false
}